soynlp/__init__.py
soynlp/hangle/__init__.py
soynlp/hangle/_distance.py
soynlp/hangle/_hangle.py
soynlp/lemmatizer/__init__.py
soynlp/lemmatizer/_conjugation.py
soynlp/lemmatizer/_lemmatizer.py
soynlp/lemmatizer/dictionary/default/Eomi/Eomi.txt
soynlp/lemmatizer/dictionary/default/EomiR/Eomi.txt
soynlp/lemmatizer/dictionary/default/Stem/Adjective.txt
soynlp/lemmatizer/dictionary/default/Stem/Verb.txt
soynlp/lemmatizer/dictionary/default/StemL/Adjective.txt
soynlp/lemmatizer/dictionary/default/StemL/Verb.txt
soynlp/ner/__init__.py
soynlp/ner/_rules.py
soynlp/normalizer/__init__.py
soynlp/normalizer/_normalizer.py
soynlp/noun/__init__.py
soynlp/noun/_josa.py
soynlp/noun/_noun_news.py
soynlp/noun/_noun_postprocessing.py
soynlp/noun/_noun_ver1.py
soynlp/noun/_noun_ver2.py
soynlp/noun/frequent_enrolled_josa.txt
soynlp/noun/frequent_noun_suffix.txt
soynlp/pos/__init__.py
soynlp/pos/_adverb.py
soynlp/pos/_chat_pos.py
soynlp/pos/_news_pos.py
soynlp/postagger/__init__.py
soynlp/postagger/_dictionary.py
soynlp/postagger/_evaluator.py
soynlp/postagger/_lrtagger.py
soynlp/postagger/_maxscore.py
soynlp/postagger/_pos_extractor.py
soynlp/postagger/_tagger.py
soynlp/postagger/_template.py
soynlp/postagger/dictionary/default/Adjective/adjective.txt
soynlp/postagger/dictionary/default/Adverb/adverb.txt
soynlp/postagger/dictionary/default/Determiner/determiner.txt
soynlp/postagger/dictionary/default/Exclamation/exclamation.txt
soynlp/postagger/dictionary/default/Josa/josa.txt
soynlp/postagger/dictionary/default/Josa/josa_chat.txt
soynlp/postagger/dictionary/default/Noun/noun.txt
soynlp/postagger/dictionary/default/Numeral/numeral.txt
soynlp/postagger/dictionary/default/Pronoun/pronoun.txt
soynlp/postagger/dictionary/default/Verb/verb.txt
soynlp/postagger/tagset/__init__.py
soynlp/postagger/tagset/soy.py
soynlp/predicator/__init__.py
soynlp/predicator/_adjective_vs_verb.py
soynlp/predicator/_eomi.py
soynlp/predicator/_predicator.py
soynlp/predicator/_stem.py
soynlp-0.0.493.dist-info/METADATA
soynlp-0.0.493.dist-info/WHEEL
soynlp-0.0.493.dist-info/top_level.txt
soynlp-0.0.493.dist-info/RECORD
