Metadata-Version: 2.1
Name: soynlp
Version: 0.0.493
Summary: Unsupervised Korean Natural Language Processing Toolkits
Home-page: https://github.com/lovit/soynlp
Author: Lovit
Author-email: soy.lovit@gmail.com
License: UNKNOWN
Keywords: korean-nlp,korean-text-processing,nlp,tokenizer,postagging,word-extraction
Platform: UNKNOWN
Classifier: Programming Language :: Python :: 3.6
Classifier: License :: OSI Approved :: GNU General Public License v3 (GPLv3)
Classifier: Operating System :: OS Independent
